mortal_ssh/__init__.py
mortal_ssh/ssh_main.cpython-312-x86_64-linux-gnu.so
mortal_ssh/sshtunnel.cpython-312-x86_64-linux-gnu.so
mortal_ssh-4.3.0.dist-info/METADATA
mortal_ssh-4.3.0.dist-info/WHEEL
mortal_ssh-4.3.0.dist-info/top_level.txt
mortal_ssh-4.3.0.dist-info/RECORD
